gh_release_install/__init__.py
gh_release_install/checksum.py
gh_release_install/cli.py
gh_release_install/main.py
gh_release_install/unpack.py
gh_release_install-0.12.0.dist-info/licenses/LICENSE
gh_release_install-0.12.0.dist-info/METADATA
gh_release_install-0.12.0.dist-info/WHEEL
gh_release_install-0.12.0.dist-info/entry_points.txt
gh_release_install-0.12.0.dist-info/top_level.txt
gh_release_install-0.12.0.dist-info/RECORD
