Metadata-Version: 2.4
Name: gh_release_install
Version: 0.12.0
Summary: CLI helper to install Github releases on your system.
Author-email: Joola <jooola@users.noreply.github.com>
Classifier: Development Status :: 3 - Alpha
Classifier: Environment :: Console
Classifier: Programming Language :: Python
Classifier: Programming Language :: Python :: 3
Classifier: Programming Language :: Python :: 3.10
Classifier: Programming Language :: Python :: 3.11
Classifier: Programming Language :: Python :: 3.12
Classifier: Programming Language :: Python :: 3.13
Classifier: Topic :: System :: Installation/Setup
Classifier: Topic :: System :: Software Distribution
Requires-Python: >=3.10
License-File: LICENSE
Requires-Dist: requests<2.33,>=2.32.3
Provides-Extra: dev
Requires-Dist: black<25.10,>=25.9; extra == "dev"
Requires-Dist: isort<6.2,>=6.1; extra == "dev"
Requires-Dist: mypy<2.0,>=1.0.0; extra == "dev"
Requires-Dist: pylint<4.0,>=3.0.0; extra == "dev"
Requires-Dist: pytest<9.0,>=8.0.0; extra == "dev"
Requires-Dist: pytest-cov<7.1,>=7; extra == "dev"
Requires-Dist: pytest-xdist<4.0,>=3.0.0; extra == "dev"
Requires-Dist: requests-mock<2.0,>=1.9.3; extra == "dev"
Requires-Dist: types-requests<3.0,>=2.31.0; extra == "dev"
Dynamic: license-file
